Metadata-Version: 2.1
Name: odoo13-addon-account-invoice-date-due
Version: 13.0.1.0.1
Summary: Update Invoice's Due Date
Home-page: https://github.com/OCA/account-invoicing
Author: Vauxoo,Odoo Community Association (OCA)
Author-email: support@odoo-community.org
License: AGPL-3
Platform: UNKNOWN
Classifier: Programming Language :: Python
Classifier: Framework :: Odoo
Classifier: License :: OSI Approved :: GNU Affero General Public License v3
Requires-Python: >=3.5
Requires-Dist: odoo (<13.1dev,>=13.0a)
